{
  "type": "gesture",
  "activeJoints": [
    "r_elbow",
    "r_hand"
  ],
  "loop": false,
  "keyframes": [
    {
      "dur": 0.3,
      "r_elbow": [
        21,
        -27
      ],
      "r_hand": [
        28,
        -3
      ]
    },
    {
      "dur": 0.3,
      "r_elbow": [
        22,
        -28
      ],
      "r_hand": [
        21,
        -3
      ]
    },
    {
      "dur": 0.3,
      "r_elbow": [
        23,
        -30
      ],
      "r_hand": [
        1,
        -18
      ]
    },
    {
      "dur": 0.3,
      "r_elbow": [
        24,
        -31
      ],
      "r_hand": [
        0,
        -37
      ]
    },
    {
      "dur": 0.3,
      "r_elbow": [
        22,
        -29
      ],
      "r_hand": [
        -3,
        -31
      ]
    },
    {
      "dur": 0.3,
      "r_elbow": [
        22,
        -29
      ],
      "r_hand": [
        -2,
        -37
      ]
    },
    {
      "dur": 0.3,
      "r_elbow": [
        23,
        -29
      ],
      "r_hand": [
        1,
        -17
      ]
    },
    {
      "dur": 0.3,
      "r_elbow": [
        23,
        -29
      ],
      "r_hand": [
        24,
        -4
      ]
    },
    {
      "dur": 0.3,
      "r_elbow": [
        23,
        -29
      ],
      "r_hand": [
        32,
        -6
      ]
    }
  ]
}
