{
  "id": "wave",
  "kind": "overlay",
  "activeJoints": [
    "r_elbow",
    "r_hand"
  ],
  "keyframes": [
    {
      "dur": 0.2
    },
    {
      "dur": 0.2,
      "r_elbow": [
        4,
        -4
      ],
      "r_hand": [
        3,
        -4
      ]
    },
    {
      "dur": 0.2,
      "r_elbow": [
        11,
        -22
      ],
      "r_hand": [
        29,
        -45
      ]
    },
    {
      "dur": 0.2,
      "r_elbow": [
        8,
        -36
      ],
      "r_hand": [
        12,
        -83
      ]
    },
    {
      "dur": 0.2,
      "r_elbow": [
        3,
        -43
      ],
      "r_hand": [
        3,
        -91
      ]
    },
    {
      "dur": 0.2,
      "r_elbow": [
        7,
        -37
      ],
      "r_hand": [
        18,
        -79
      ]
    },
    {
      "dur": 0.2,
      "r_elbow": [
        10,
        -31
      ],
      "r_hand": [
        28,
        -52
      ]
    },
    {
      "dur": 0.2,
      "r_elbow": [
        11,
        -23
      ],
      "r_hand": [
        25,
        -34
      ]
    },
    {
      "dur": 0.2,
      "r_elbow": [
        10,
        -31
      ],
      "r_hand": [
        28,
        -52
      ]
    },
    {
      "dur": 0.2,
      "r_elbow": [
        7,
        -37
      ],
      "r_hand": [
        18,
        -79
      ]
    },
    {
      "dur": 0.2,
      "r_elbow": [
        3,
        -43
      ],
      "r_hand": [
        3,
        -91
      ]
    },
    {
      "dur": 0.2,
      "r_elbow": [
        7,
        -37
      ],
      "r_hand": [
        18,
        -79
      ]
    },
    {
      "dur": 0.2,
      "r_elbow": [
        10,
        -31
      ],
      "r_hand": [
        28,
        -52
      ]
    },
    {
      "dur": 0.2,
      "r_elbow": [
        11,
        -23
      ],
      "r_hand": [
        25,
        -34
      ]
    },
    {
      "dur": 0.2,
      "r_elbow": [
        11,
        -20
      ],
      "r_hand": [
        22,
        -27
      ]
    },
    {
      "dur": 0.2,
      "r_elbow": [
        10,
        -16
      ],
      "r_hand": [
        18,
        -20
      ]
    },
    {
      "dur": 0.2,
      "r_elbow": [
        9,
        -13
      ],
      "r_hand": [
        13,
        -14
      ]
    },
    {
      "dur": 0.2,
      "r_elbow": [
        7,
        -9
      ],
      "r_hand": [
        7,
        -9
      ]
    }
  ]
}